biliup/__init__.py
biliup/__main__.py
biliup/app.py
biliup/config.py
biliup/downloader.py
biliup/handler.py
biliup/uploader.py
biliup/Danmaku/__init__.py
biliup/Danmaku/bilibili.py
biliup/Danmaku/douyin.py
biliup/Danmaku/douyu.py
biliup/Danmaku/huya.py
biliup/Danmaku/twitcasting.py
biliup/Danmaku/twitch.py
biliup/Danmaku/youtube.py
biliup/Danmaku/douyin_util/__init__.py
biliup/Danmaku/douyin_util/dy_pb2.py
biliup/Danmaku/douyin_util/dy_pb2.pyi
biliup/Danmaku/douyin_util/get_signature_test.py
biliup/Danmaku/douyin_util/webmssdk.js
biliup/Danmaku/paramgen/__init__.py
biliup/Danmaku/paramgen/arcparam.py
biliup/Danmaku/paramgen/enc.py
biliup/Danmaku/paramgen/liveparam.py
biliup/Danmaku/tars/EndpointF.py
biliup/Danmaku/tars/QueryF.py
biliup/Danmaku/tars/__TimeoutQueue.py
biliup/Danmaku/tars/__adapterproxy.py
biliup/Danmaku/tars/__async.py
biliup/Danmaku/tars/__init__.py
biliup/Danmaku/tars/__logger.py
biliup/Danmaku/tars/__packet.py
biliup/Danmaku/tars/__rpc.py
biliup/Danmaku/tars/__servantproxy.py
biliup/Danmaku/tars/__tars.py
biliup/Danmaku/tars/__trans.py
biliup/Danmaku/tars/__tup.py
biliup/Danmaku/tars/__util.py
biliup/Danmaku/tars/core.py
biliup/Danmaku/tars/exception.py
biliup/Danmaku/tars/tars/__init__.py
biliup/common/Daemon.py
biliup/common/__init__.py
biliup/common/configlog.ini
biliup/common/log.py
biliup/common/reload.py
biliup/common/timer.py
biliup/common/tools.py
biliup/common/util.py
biliup/database/__init__.py
biliup/database/db.py
biliup/database/models.py
biliup/database/migration/env.py
biliup/database/migration/script.py.mako
biliup/engine/__init__.py
biliup/engine/decorators.py
biliup/engine/download.py
biliup/engine/event.py
biliup/engine/upload.py
biliup/plugins/__init__.py
biliup/plugins/acfun.py
biliup/plugins/afreecaTV.py
biliup/plugins/bigo.py
biliup/plugins/bili_chromeup.py
biliup/plugins/bili_webup.py
biliup/plugins/bilibili.py
biliup/plugins/biliuprs.py
biliup/plugins/cc.py
biliup/plugins/douyin.py
biliup/plugins/douyu.py
xueba_biliup-0.4.78.dist-info/LICENSE
xueba_biliup-0.4.78.dist-info/METADATA
xueba_biliup-0.4.78.dist-info/WHEEL
xueba_biliup-0.4.78.dist-info/entry_points.txt
xueba_biliup-0.4.78.dist-info/top_level.txt
xueba_biliup-0.4.78.dist-info/RECORD
